downlow/__init__.py
downlow/download.py
downlow/downlow_data_classes.py
downlow/utils.py
downlow-0.0.6.dist-info/METADATA
downlow-0.0.6.dist-info/WHEEL
downlow-0.0.6.dist-info/entry_points.txt
downlow-0.0.6.dist-info/licenses/LICENSE
downlow-0.0.6.dist-info/RECORD
