Metadata-Version: 2.4
Name: downlow
Version: 0.0.6
Summary: A bulk downloader with tenacity and grace
Project-URL: Homepage, https://willf.github.io/downlow/
Project-URL: Repository, https://github.com/willf/downlow
Project-URL: Documentation, https://willf.github.io/downlow/
Author-email: Will Fitzgerald <will.fitzgerald@gmail.com>
License-File: LICENSE
Keywords: python
Classifier: Intended Audience :: Developers
Classifier: Programming Language :: Python
Classifier: Programming Language :: Python :: 3
Classifier: Programming Language :: Python :: 3.9
Classifier: Programming Language :: Python :: 3.10
Classifier: Programming Language :: Python :: 3.11
Classifier: Programming Language :: Python :: 3.12
Classifier: Programming Language :: Python :: 3.13
Classifier: Topic :: Software Development :: Libraries :: Python Modules
Requires-Python: >=3.9
Requires-Dist: click>=8.1.8
Requires-Dist: loguru>=0.7.3
Requires-Dist: rich>=13.9.4
Requires-Dist: tldextract>=5.1.3
